odoo/addons/l10n_es_aeat_mod190/README.rst
odoo/addons/l10n_es_aeat_mod190/__init__.py
odoo/addons/l10n_es_aeat_mod190/__manifest__.py
odoo/addons/l10n_es_aeat_mod190/data/aeat_export_mod190_data.xml
odoo/addons/l10n_es_aeat_mod190/data/aeat_export_mod190_partner_data.xml
odoo/addons/l10n_es_aeat_mod190/data/perception_key_data.xml
odoo/addons/l10n_es_aeat_mod190/data/perception_subkey_data.xml
odoo/addons/l10n_es_aeat_mod190/data/tax_code_map_mod190_data.xml
odoo/addons/l10n_es_aeat_mod190/docs/DR190_2017.pdf
odoo/addons/l10n_es_aeat_mod190/i18n/l10n_es_aeat_mod190.pot
odoo/addons/l10n_es_aeat_mod190/migrations/11.0.2.0.0/post-migration.py
odoo/addons/l10n_es_aeat_mod190/models/__init__.py
odoo/addons/l10n_es_aeat_mod190/models/account_fiscal_position.py
odoo/addons/l10n_es_aeat_mod190/models/account_invoice.py
odoo/addons/l10n_es_aeat_mod190/models/account_move_line.py
odoo/addons/l10n_es_aeat_mod190/models/l10n_es_aeat_mod190_report.py
odoo/addons/l10n_es_aeat_mod190/models/l10n_es_aeat_perception.py
odoo/addons/l10n_es_aeat_mod190/models/l10n_es_mod190_additional_data_mixin.py
odoo/addons/l10n_es_aeat_mod190/models/l10n_es_mod190_mixin.py
odoo/addons/l10n_es_aeat_mod190/models/res_partner.py
odoo/addons/l10n_es_aeat_mod190/readme/CONTRIBUTORS.rst
odoo/addons/l10n_es_aeat_mod190/readme/DESCRIPTION.rst
odoo/addons/l10n_es_aeat_mod190/readme/USAGE.rst
odoo/addons/l10n_es_aeat_mod190/security/ir.model.access.csv
odoo/addons/l10n_es_aeat_mod190/security/l10n_es_aeat_mod190_security.xml
odoo/addons/l10n_es_aeat_mod190/static/description/icon.png
odoo/addons/l10n_es_aeat_mod190/static/description/icon_source.svg
odoo/addons/l10n_es_aeat_mod190/static/description/index.html
odoo/addons/l10n_es_aeat_mod190/tests/__init__.py
odoo/addons/l10n_es_aeat_mod190/tests/test_mod190.py
odoo/addons/l10n_es_aeat_mod190/views/account_fiscal_position.xml
odoo/addons/l10n_es_aeat_mod190/views/account_invoice_view.xml
odoo/addons/l10n_es_aeat_mod190/views/account_move_view.xml
odoo11_addon_l10n_es_aeat_mod190-11.0.2.0.1.dist-info/METADATA
odoo11_addon_l10n_es_aeat_mod190-11.0.2.0.1.dist-info/WHEEL
odoo11_addon_l10n_es_aeat_mod190-11.0.2.0.1.dist-info/top_level.txt
odoo11_addon_l10n_es_aeat_mod190-11.0.2.0.1.dist-info/RECORD
